Metadata-Version: 1.1
Name: wsgicors
Version: 0.7.0
Summary: WSGI for Cross Origin Resource Sharing (CORS)
Home-page: https://github.com/may-day/wsgicors
Author: Norman Krämer
Author-email: kraemer.norman@googlemail.com
License: Apache Software License 2.0
Keywords: wsgi,cors
Platform: UNKNOWN
Classifier: License :: OSI Approved :: Apache Software License
Classifier: Programming Language :: Python :: 2
Classifier: Programming Language :: Python :: 3
Classifier: Development Status :: 3 - Alpha
Classifier: Environment :: Web Environment
Classifier: Intended Audience :: Developers
Classifier: Topic :: Software Development :: Libraries :: Python Modules
Classifier: Topic :: Internet :: WWW/HTTP :: WSGI
